{
  "timestamp": "2026-04-16T15:17:31.390107+00:00",
  "regime": {
    "regime": "STRONG UPTREND",
    "bull_count": 11,
    "bear_count": 4,
    "neutral_count": 0,
    "avg_rsi": 60.6,
    "actionable_count": 1,
    "sizing_advice": "SIZE UP \u2014 Full positions, environment favors momentum.",
    "description": "11/15 bullish. Aggressive pullback entries.",
    "regime_multiplier": 1.5,
    "spy_above_21ema": true
  },
  "signals": [
    {
      "ticker": "NVDA",
      "name": "NVIDIA",
      "weight": 7.83,
      "sector": "Tech",
      "current_price": 199.39,
      "ema8": 191.09,
      "ema21": 184.66,
      "ema50": 183.42,
      "rsi": 70.2,
      "vol_ratio": 0.86,
      "change_1d": 0.26,
      "change_5d": 8.42,
      "change_20d": 10.53,
      "bull_stacked": true,
      "bear_stacked": false,
      "ema_spread": 4.18,
      "dist_to_8": 4.35,
      "dist_to_21": 7.98,
      "is_pullback_buy": false,
      "is_pullback_sell": false,
      "signal": "BUY",
      "signal_strength": 3,
      "action_note": "Trend up, EMAs stacked. Wait for pullback to 8 EMA ($191.09).",
      "stop_loss": 165.09,
      "target_1": 285.14,
      "target_2": 319.44,
      "risk_per_share": 34.3,
      "position_size": 0,
      "support": 164.27,
      "resistance": 200.4,
      "conviction_score": 50.0
    },
    {
      "ticker": "AAPL",
      "name": "Apple",
      "weight": 6.47,
      "sector": "Tech",
      "current_price": 262.51,
      "ema8": 260.43,
      "ema21": 257.98,
      "ema50": 259.29,
      "rsi": 56.2,
      "vol_ratio": 0.87,
      "change_1d": -1.47,
      "change_5d": 0.78,
      "change_20d": 5.03,
      "bull_stacked": false,
      "bear_stacked": false,
      "ema_spread": 0.44,
      "dist_to_8": 0.8,
      "dist_to_21": 1.76,
      "is_pullback_buy": false,
      "is_pullback_sell": false,
      "signal": "LEAN BULL",
      "signal_strength": 2,
      "action_note": "Developing bullish trend. Wait for full EMA stack.",
      "stop_loss": 245.51,
      "target_1": 305.01,
      "target_2": 322.01,
      "risk_per_share": 17.0,
      "position_size": 1,
      "support": 245.51,
      "resistance": 267.16,
      "conviction_score": 25.0
    },
    {
      "ticker": "MSFT",
      "name": "Microsoft",
      "weight": 5.39,
      "sector": "Tech",
      "current_price": 416.51,
      "ema8": 392.85,
      "ema21": 386.21,
      "ema50": 398.66,
      "rsi": 69.4,
      "vol_ratio": 0.98,
      "change_1d": 1.29,
      "change_5d": 11.64,
      "change_20d": 6.31,
      "bull_stacked": false,
      "bear_stacked": false,
      "ema_spread": -1.46,
      "dist_to_8": 6.02,
      "dist_to_21": 7.85,
      "is_pullback_buy": false,
      "is_pullback_sell": false,
      "signal": "LEAN BULL",
      "signal_strength": 2,
      "action_note": "Developing bullish trend. Wait for full EMA stack.",
      "stop_loss": 356.28,
      "target_1": 567.09,
      "target_2": 627.32,
      "risk_per_share": 60.23,
      "position_size": 0,
      "support": 356.28,
      "resistance": 420.0,
      "conviction_score": 20.0
    },
    {
      "ticker": "AMZN",
      "name": "Amazon",
      "weight": 3.93,
      "sector": "Consumer",
      "current_price": 247.65,
      "ema8": 237.75,
      "ema21": 225.19,
      "ema50": 220.68,
      "rsi": 74.5,
      "vol_ratio": 1.02,
      "change_1d": -0.34,
      "change_5d": 5.99,
      "change_20d": 18.0,
      "bull_stacked": true,
      "bear_stacked": false,
      "ema_spread": 7.73,
      "dist_to_8": 4.17,
      "dist_to_21": 9.98,
      "is_pullback_buy": false,
      "is_pullback_sell": false,
      "signal": "BUY",
      "signal_strength": 3,
      "action_note": "Trend up, EMAs stacked. Wait for pullback to 8 EMA ($237.75).",
      "stop_loss": 200.14,
      "target_1": 366.44,
      "target_2": 413.95,
      "risk_per_share": 47.51,
      "position_size": 0,
      "support": 199.14,
      "resistance": 252.18,
      "conviction_score": 50.0
    },
    {
      "ticker": "GOOGL",
      "name": "Alphabet",
      "weight": 3.32,
      "sector": "Tech",
      "current_price": 337.95,
      "ema8": 324.16,
      "ema21": 312.17,
      "ema50": 310.2,
      "rsi": 71.7,
      "vol_ratio": 0.67,
      "change_1d": 0.25,
      "change_5d": 6.11,
      "change_20d": 9.83,
      "bull_stacked": true,
      "bear_stacked": false,
      "ema_spread": 4.5,
      "dist_to_8": 4.25,
      "dist_to_21": 8.26,
      "is_pullback_buy": false,
      "is_pullback_sell": false,
      "signal": "BUY",
      "signal_strength": 3,
      "action_note": "Trend up, EMAs stacked. Wait for pullback to 8 EMA ($324.16).",
      "stop_loss": 273.47,
      "target_1": 499.15,
      "target_2": 563.63,
      "risk_per_share": 64.48,
      "position_size": 0,
      "support": 272.11,
      "resistance": 339.88,
      "conviction_score": 50.0
    },
    {
      "ticker": "AVGO",
      "name": "Broadcom",
      "weight": 2.64,
      "sector": "Tech",
      "current_price": 399.48,
      "ema8": 372.71,
      "ema21": 348.13,
      "ema50": 337.7,
      "rsi": 77.7,
      "vol_ratio": 0.95,
      "change_1d": 0.7,
      "change_5d": 12.56,
      "change_20d": 26.45,
      "bull_stacked": true,
      "bear_stacked": false,
      "ema_spread": 10.37,
      "dist_to_8": 7.18,
      "dist_to_21": 14.75,
      "is_pullback_buy": false,
      "is_pullback_sell": false,
      "signal": "BUY",
      "signal_strength": 3,
      "action_note": "Trend up, EMAs stacked. Wait for pullback to 8 EMA ($372.71).",
      "stop_loss": 291.41,
      "target_1": 669.66,
      "target_2": 777.73,
      "risk_per_share": 108.07,
      "position_size": 0,
      "support": 289.96,
      "resistance": 399.68,
      "conviction_score": 45.0
    },
    {
      "ticker": "META",
      "name": "Meta",
      "weight": 2.63,
      "sector": "Tech",
      "current_price": 674.43,
      "ema8": 641.14,
      "ema21": 620.0,
      "ema50": 625.84,
      "rsi": 67.2,
      "vol_ratio": 0.65,
      "change_1d": 0.43,
      "change_5d": 7.33,
      "change_20d": 9.54,
      "bull_stacked": false,
      "bear_stacked": false,
      "ema_spread": 2.44,
      "dist_to_8": 5.19,
      "dist_to_21": 8.78,
      "is_pullback_buy": false,
      "is_pullback_sell": false,
      "signal": "LEAN BULL",
      "signal_strength": 2,
      "action_note": "Developing bullish trend. Wait for full EMA stack.",
      "stop_loss": 520.26,
      "target_1": 1059.87,
      "target_2": 1214.05,
      "risk_per_share": 154.17,
      "position_size": 0,
      "support": 520.26,
      "resistance": 678.5,
      "conviction_score": 20.0
    },
    {
      "ticker": "TSLA",
      "name": "Tesla",
      "weight": 2.04,
      "sector": "Consumer",
      "current_price": 387.29,
      "ema8": 369.2,
      "ema21": 371.21,
      "ema50": 388.49,
      "rsi": 55.5,
      "vol_ratio": 0.92,
      "change_1d": -1.19,
      "change_5d": 12.06,
      "change_20d": -1.4,
      "bull_stacked": false,
      "bear_stacked": true,
      "ema_spread": -4.97,
      "dist_to_8": 4.9,
      "dist_to_21": 4.33,
      "is_pullback_buy": false,
      "is_pullback_sell": false,
      "signal": "SELL",
      "signal_strength": -3,
      "action_note": "Trend down. Wait for bounce to 8 EMA ($369.20) for puts.",
      "stop_loss": 394.25,
      "target_1": 369.89,
      "target_2": 362.93,
      "risk_per_share": 6.96,
      "position_size": 2,
      "support": 337.24,
      "resistance": 396.23,
      "conviction_score": 45.0
    },
    {
      "ticker": "BRK.B",
      "name": "Berkshire",
      "weight": 1.49,
      "sector": "Finance",
      "current_price": 473.57,
      "ema8": 477.13,
      "ema21": 479.9,
      "ema50": 485.2,
      "rsi": 39.6,
      "vol_ratio": 0.97,
      "change_1d": -0.11,
      "change_5d": -2.4,
      "change_20d": -2.25,
      "bull_stacked": false,
      "bear_stacked": true,
      "ema_spread": -1.66,
      "dist_to_8": -0.75,
      "dist_to_21": -1.32,
      "is_pullback_buy": false,
      "is_pullback_sell": false,
      "signal": "SELL",
      "signal_strength": -3,
      "action_note": "Trend down. Wait for bounce to 8 EMA ($477.13) for puts.",
      "stop_loss": 485.51,
      "target_1": 443.72,
      "target_2": 431.78,
      "risk_per_share": 11.94,
      "position_size": 1,
      "support": 467.15,
      "resistance": 487.95,
      "conviction_score": 50.0
    },
    {
      "ticker": "JPM",
      "name": "JPMorgan",
      "weight": 1.35,
      "sector": "Finance",
      "current_price": 308.78,
      "ema8": 306.63,
      "ema21": 300.96,
      "ema50": 301.11,
      "rsi": 60.1,
      "vol_ratio": 0.77,
      "change_1d": 0.93,
      "change_5d": -0.5,
      "change_20d": 7.31,
      "bull_stacked": false,
      "bear_stacked": false,
      "ema_spread": 1.83,
      "dist_to_8": 0.7,
      "dist_to_21": 2.6,
      "is_pullback_buy": false,
      "is_pullback_sell": false,
      "signal": "LEAN BULL",
      "signal_strength": 2,
      "action_note": "Developing bullish trend. Wait for full EMA stack.",
      "stop_loss": 281.75,
      "target_1": 376.36,
      "target_2": 403.39,
      "risk_per_share": 27.03,
      "position_size": 0,
      "support": 281.75,
      "resistance": 314.32,
      "conviction_score": 15.0
    },
    {
      "ticker": "LLY",
      "name": "Eli Lilly",
      "weight": 1.3,
      "sector": "Health",
      "current_price": 911.57,
      "ema8": 923.22,
      "ema21": 934.06,
      "ema50": 967.09,
      "rsi": 41.9,
      "vol_ratio": 0.82,
      "change_1d": 0.72,
      "change_5d": -4.57,
      "change_20d": -0.71,
      "bull_stacked": false,
      "bear_stacked": true,
      "ema_spread": -4.54,
      "dist_to_8": -1.26,
      "dist_to_21": -2.41,
      "is_pullback_buy": false,
      "is_pullback_sell": false,
      "signal": "SELL",
      "signal_strength": -3,
      "action_note": "Trend down. Wait for bounce to 8 EMA ($923.22) for puts.",
      "stop_loss": 971.8,
      "target_1": 760.99,
      "target_2": 700.75,
      "risk_per_share": 60.23,
      "position_size": 0,
      "support": 877.11,
      "resistance": 976.68,
      "conviction_score": 55.0
    },
    {
      "ticker": "V",
      "name": "Visa",
      "weight": 1.1,
      "sector": "Finance",
      "current_price": 315.57,
      "ema8": 310.36,
      "ema21": 308.09,
      "ema50": 313.64,
      "rsi": 58.8,
      "vol_ratio": 0.7,
      "change_1d": -0.11,
      "change_5d": 2.36,
      "change_20d": 5.53,
      "bull_stacked": false,
      "bear_stacked": false,
      "ema_spread": -1.04,
      "dist_to_8": 1.68,
      "dist_to_21": 2.43,
      "is_pullback_buy": false,
      "is_pullback_sell": false,
      "signal": "LEAN BULL",
      "signal_strength": 2,
      "action_note": "Developing bullish trend. Wait for full EMA stack.",
      "stop_loss": 293.89,
      "target_1": 369.75,
      "target_2": 391.43,
      "risk_per_share": 21.67,
      "position_size": 0,
      "support": 293.89,
      "resistance": 318.0,
      "conviction_score": 20.0
    },
    {
      "ticker": "UNH",
      "name": "UnitedHealth",
      "weight": 1.05,
      "sector": "Health",
      "current_price": 313.9,
      "ema8": 306.68,
      "ema21": 294.88,
      "ema50": 293.7,
      "rsi": 68.2,
      "vol_ratio": 0.54,
      "change_1d": -0.05,
      "change_5d": 2.28,
      "change_20d": 10.4,
      "bull_stacked": true,
      "bear_stacked": false,
      "ema_spread": 4.42,
      "dist_to_8": 2.36,
      "dist_to_21": 6.45,
      "is_pullback_buy": false,
      "is_pullback_sell": false,
      "signal": "BUY",
      "signal_strength": 3,
      "action_note": "Trend up, EMAs stacked. Wait for pullback to 8 EMA ($306.68).",
      "stop_loss": 257.25,
      "target_1": 455.53,
      "target_2": 512.18,
      "risk_per_share": 56.65,
      "position_size": 0,
      "support": 255.97,
      "resistance": 319.62,
      "conviction_score": 50.0
    },
    {
      "ticker": "COST",
      "name": "Costco",
      "weight": 0.98,
      "sector": "Consumer",
      "current_price": 987.96,
      "ema8": 993.19,
      "ema21": 995.04,
      "ema50": 984.28,
      "rsi": 47.5,
      "vol_ratio": 1.07,
      "change_1d": 0.33,
      "change_5d": -4.27,
      "change_20d": 0.82,
      "bull_stacked": false,
      "bear_stacked": false,
      "ema_spread": 0.9,
      "dist_to_8": -0.53,
      "dist_to_21": -0.71,
      "is_pullback_buy": false,
      "is_pullback_sell": false,
      "signal": "LEAN BEAR",
      "signal_strength": -2,
      "action_note": "Bearish momentum developing. Wait for full stack.",
      "stop_loss": 1035.82,
      "target_1": 868.31,
      "target_2": 820.45,
      "risk_per_share": 47.86,
      "position_size": 0,
      "support": 961.0,
      "resistance": 1035.82,
      "conviction_score": 20.0
    },
    {
      "ticker": "WMT",
      "name": "Walmart",
      "weight": 0.92,
      "sector": "Consumer",
      "current_price": 124.93,
      "ema8": 125.27,
      "ema21": 124.88,
      "ema50": 123.81,
      "rsi": 50.5,
      "vol_ratio": 0.72,
      "change_1d": 0.13,
      "change_5d": -3.26,
      "change_20d": 2.41,
      "bull_stacked": true,
      "bear_stacked": false,
      "ema_spread": 1.18,
      "dist_to_8": -0.27,
      "dist_to_21": 0.04,
      "is_pullback_buy": true,
      "is_pullback_sell": false,
      "signal": "PULLBACK BUY",
      "signal_strength": 5,
      "action_note": "Price at 8 EMA ($125.27) in uptrend + declining vol (0.7x). A+ call entry.",
      "stop_loss": 118.61,
      "target_1": 140.71,
      "target_2": 147.03,
      "risk_per_share": 6.31,
      "position_size": 3,
      "support": 118.02,
      "resistance": 129.69,
      "conviction_score": 85.0
    }
  ],
  "buy_orders": [
    {
      "action": "BUY",
      "ticker": "WMT",
      "name": "Walmart",
      "price": 124.93,
      "shares": 3.58,
      "dollar_amount": 447.25,
      "portfolio_pct": 44.7,
      "stop_loss": 118.61,
      "target": 140.71,
      "risk_reward": "2.5:1",
      "reason": "Price at 8 EMA ($125.27) in uptrend + declining vol (0.7x). A+ call entry.",
      "priority": 1,
      "option_type": "SHARES \u2014 Market or limit order",
      "signal": "PULLBACK BUY",
      "conviction": 85.0
    },
    {
      "action": "BUY",
      "ticker": "NVDA",
      "name": "NVIDIA",
      "price": 199.39,
      "shares": 1.32,
      "dollar_amount": 263.19,
      "portfolio_pct": 26.3,
      "stop_loss": 165.09,
      "target": 285.14,
      "risk_reward": "2.5:1",
      "reason": "Trend up, EMAs stacked. Wait for pullback to 8 EMA ($191.09).",
      "priority": 2,
      "option_type": "SHARES \u2014 Market or limit order",
      "signal": "BUY",
      "conviction": 50.0
    },
    {
      "action": "BUY",
      "ticker": "AMZN",
      "name": "Amazon",
      "price": 247.65,
      "shares": 1.06,
      "dollar_amount": 262.51,
      "portfolio_pct": 26.3,
      "stop_loss": 200.14,
      "target": 366.44,
      "risk_reward": "2.5:1",
      "reason": "Trend up, EMAs stacked. Wait for pullback to 8 EMA ($237.75).",
      "priority": 3,
      "option_type": "SHARES \u2014 Market or limit order",
      "signal": "BUY",
      "conviction": 50.0
    },
    {
      "action": "BUY",
      "ticker": "GOOGL",
      "name": "Alphabet",
      "price": 337.95,
      "shares": 0.78,
      "dollar_amount": 263.6,
      "portfolio_pct": 26.4,
      "stop_loss": 273.47,
      "target": 499.15,
      "risk_reward": "2.5:1",
      "reason": "Trend up, EMAs stacked. Wait for pullback to 8 EMA ($324.16).",
      "priority": 4,
      "option_type": "SHARES \u2014 Market or limit order",
      "signal": "BUY",
      "conviction": 50.0
    },
    {
      "action": "BUY",
      "ticker": "UNH",
      "name": "UnitedHealth",
      "price": 313.9,
      "shares": 0.84,
      "dollar_amount": 263.68,
      "portfolio_pct": 26.4,
      "stop_loss": 257.25,
      "target": 455.53,
      "risk_reward": "2.5:1",
      "reason": "Trend up, EMAs stacked. Wait for pullback to 8 EMA ($306.68).",
      "priority": 5,
      "option_type": "SHARES \u2014 Market or limit order",
      "signal": "BUY",
      "conviction": 50.0
    }
  ],
  "sell_orders": [],
  "manage_orders": []
}